totp_generator/__init__.py
totp_generator/cli.py
totp_generator/core_utils.py
totp_generator-3.1.4.dist-info/licenses/LICENSE
totp_generator-3.1.4.dist-info/METADATA
totp_generator-3.1.4.dist-info/WHEEL
totp_generator-3.1.4.dist-info/entry_points.txt
totp_generator-3.1.4.dist-info/top_level.txt
totp_generator-3.1.4.dist-info/RECORD
