Metadata-Version: 2.4
Name: TOTP-Generator
Version: 3.1.4
Summary: Utility that generates TOTP codes and stores the TOTP secrets in your system keyring.
Author: Jeremy Falling
License-Expression: GPL-3.0-only
Project-URL: Homepage, https://codeberg.org/jjfalling/TOTP-Generator
Project-URL: Issues, https://codeberg.org/jjfalling/TOTP-Generator/issues
Classifier: Programming Language :: Python
Classifier: Programming Language :: Python :: 3
Classifier: Development Status :: 5 - Production/Stable
Classifier: Intended Audience :: End Users/Desktop
Requires-Python: >=3.9
License-File: LICENSE
Requires-Dist: keyring<26.0.0,>=23.0.0
Requires-Dist: keyrings.alt<6.0,>=4.1
Requires-Dist: pyotp<3.0.0,>=2.6.0
Requires-Dist: pyclip<1.0.0,>=0.5.4
Provides-Extra: proctitle
Requires-Dist: setproctitle<1.4.0,>=1.2.2; extra == "proctitle"
Provides-Extra: test
Requires-Dist: pytest; extra == "test"
Requires-Dist: pytest-cov>2.6; extra == "test"
Requires-Dist: mock; extra == "test"
Requires-Dist: wheel; extra == "test"
Requires-Dist: codecov; extra == "test"
Requires-Dist: pylint; extra == "test"
Dynamic: license-file
